Metadata-Version: 1.0
Name: gaussnbin-distro
Version: 0.1
Summary: Gaussian and Binomial distributions
Home-page: UNKNOWN
Author: Uchechukwu Fortune Njoku
Author-email: njokuuchechi@gmail.com
License: UNKNOWN
Platform: UNKNOWN
